simple_openai/__init__.py
simple_openai/async_simple_openai.py
simple_openai/chat_manager.py
simple_openai/constants.py
simple_openai/responses.py
simple_openai/simple_openai.py
simple_openai/tool_manager.py
simple_openai/models/__init__.py
simple_openai/models/open_ai_models.py
simple_openai-5.2.0.dist-info/licenses/LICENSE
simple_openai-5.2.0.dist-info/METADATA
simple_openai-5.2.0.dist-info/WHEEL
simple_openai-5.2.0.dist-info/top_level.txt
simple_openai-5.2.0.dist-info/RECORD
