Metadata-Version: 2.4
Name: simple-openai
Version: 5.2.0
Summary: Simple OpenAI API wrapper
Author-email: Stephen Schleising <stephen@schleising.net>
License:                                  Apache License
Project-URL: Homepage, https://schleising.github.io/simple-openai/
Project-URL: Issues, https://github.com/schleising/simple-openai/issues
Project-URL: Repo, https://github.com/schleising/simple-openai
Keywords: openai,api,wrapper
Classifier: License :: OSI Approved :: Apache Software License
Classifier: Programming Language :: Python
Classifier: Programming Language :: Python :: 3
Classifier: Programming Language :: Python :: 3.10
Classifier: Programming Language :: Python :: 3.11
Classifier: Programming Language :: Python :: 3.12
Classifier: Programming Language :: Python :: 3.13
Classifier: Programming Language :: Python :: 3.14
Classifier: Topic :: Software Development :: Libraries
Classifier: Topic :: Software Development :: Libraries :: Python Modules
Requires-Python: >=3.10
License-File: LICENSE
Requires-Dist: aiohttp
Requires-Dist: requests
Requires-Dist: pydantic
Provides-Extra: dev
Requires-Dist: mkdocs; extra == "dev"
Requires-Dist: mkdocs-material; extra == "dev"
Requires-Dist: mkdocstrings; extra == "dev"
Requires-Dist: mkdocstrings-python; extra == "dev"
Dynamic: license-file
